medview/__init__.py
medview/tmp_func.py
medview/util.py
medview/vtkViewClass.py
medview/vtktools.py
MedView-0.0.1.dist-info/LICENSE
MedView-0.0.1.dist-info/METADATA
MedView-0.0.1.dist-info/WHEEL
MedView-0.0.1.dist-info/top_level.txt
MedView-0.0.1.dist-info/RECORD
