Metadata-Version: 2.1
Name: MedView
Version: 0.0.1
Summary: 3d show tools
Home-page: https://github.com/TimothyZero/Medical-Image-Visualization
Author: timothy
Author-email: thyzyfx@qq.com
License: UNKNOWN
Platform: UNKNOWN
Classifier: Programming Language :: Python :: 3
Classifier: License :: OSI Approved :: Apache Software License
Classifier: Operating System :: OS Independent
